pigshare/__init__.py
pigshare/admin_api.py
pigshare/api.py
pigshare/caching.py
pigshare/example.py
pigshare/helpers.py
pigshare/input_helpers.py
pigshare/models.py
pigshare/pigshare.py
pigshare/stats_api.py
pigshare-0.5.3.dist-info/DESCRIPTION.rst
pigshare-0.5.3.dist-info/METADATA
pigshare-0.5.3.dist-info/RECORD
pigshare-0.5.3.dist-info/WHEEL
pigshare-0.5.3.dist-info/entry_points.txt
pigshare-0.5.3.dist-info/metadata.json
pigshare-0.5.3.dist-info/top_level.txt
