Metadata-Version: 2.0
Name: pigshare
Version: 0.5.3
Summary: Python client for figshare
Home-page: https://github.com/makkus/pigshare
Author: Markus Binsteiner
Author-email: makkus@gmail.com
License: GPLv3
Keywords: pigshare figshare client rest api
Platform: UNKNOWN
Classifier: Development Status :: 3 - Alpha
Classifier: Environment :: Console
Classifier: Intended Audience :: Developers
Classifier: Intended Audience :: Science/Research
Classifier: Intended Audience :: End Users/Desktop
Classifier: License :: OSI Approved :: GNU General Public License v3 (GPLv3)
Classifier: Natural Language :: English
Classifier: Programming Language :: Python :: 2.7
Requires-Dist: argcomplete
Requires-Dist: argparse
Requires-Dist: booby
Requires-Dist: parinx
Requires-Dist: pyclist
Requires-Dist: restkit
Requires-Dist: setuptools
Requires-Dist: simplejson
